<?xml version="1.0" encoding="UTF-8"?>
<DARoots Version="1" Minor="26">
  <FileSet Name="sources_1" Type="DesignSrcs" RelSrcDir="$PSRCDIR/sources_1">
    <Filter Type="Srcs"/>
    <File Path="$PPRDIR/../../../../../../../Program Files/System Centroid/Flowrian R7/Library/PNULib/sources/PNU_XOR2.v">
      <FileInfo>
        <Attr Name="UsedInSynthesis" Val="1"/>
        <Attr Name="UsedInImplementation" Val="1"/>
        <Attr Name="UsedInSimulation" Val="1"/>
      </FileInfo>
    </File>
    <File Path="$PPRDIR/../../../../../../../Program Files/System Centroid/Flowrian R7/Library/PNULib/sources/PNU_OR3.v">
      <FileInfo>
        <Attr Name="UsedInSynthesis" Val="1"/>
        <Attr Name="UsedInImplementation" Val="1"/>
        <Attr Name="UsedInSimulation" Val="1"/>
      </FileInfo>
    </File>
    <File Path="$PPRDIR/../../../../../../../Program Files/System Centroid/Flowrian R7/Library/PNULib/sources/PNU_OR2.v">
      <FileInfo>
        <Attr Name="UsedInSynthesis" Val="1"/>
        <Attr Name="UsedInImplementation" Val="1"/>
        <Attr Name="UsedInSimulation" Val="1"/>
      </FileInfo>
    </File>
    <File Path="$PPRDIR/../../../../../../../Program Files/System Centroid/Flowrian R7/Library/PNULib/sources/PNU_NOT.v">
      <FileInfo>
        <Attr Name="UsedInSynthesis" Val="1"/>
        <Attr Name="UsedInImplementation" Val="1"/>
        <Attr Name="UsedInSimulation" Val="1"/>
      </FileInfo>
    </File>
    <File Path="$PPRDIR/../../../../../../../Program Files/System Centroid/Flowrian R7/Library/PNULib/sources/PNU_NOR4.v">
      <FileInfo>
        <Attr Name="UsedInSynthesis" Val="1"/>
        <Attr Name="UsedInImplementation" Val="1"/>
        <Attr Name="UsedInSimulation" Val="1"/>
      </FileInfo>
    </File>
    <File Path="$PPRDIR/../../../../../../../Program Files/System Centroid/Flowrian R7/Library/PNULib/sources/PNU_DFF.v">
      <FileInfo>
        <Attr Name="UsedInSynthesis" Val="1"/>
        <Attr Name="UsedInImplementation" Val="1"/>
        <Attr Name="UsedInSimulation" Val="1"/>
      </FileInfo>
    </File>
    <File Path="$PPRDIR/../../../../../../../Program Files/System Centroid/Flowrian R7/Library/PNULib/sources/PNU_AND3.v">
      <FileInfo>
        <Attr Name="UsedInSynthesis" Val="1"/>
        <Attr Name="UsedInImplementation" Val="1"/>
        <Attr Name="UsedInSimulation" Val="1"/>
      </FileInfo>
    </File>
    <File Path="$PPRDIR/../../../../../../../Program Files/System Centroid/Flowrian R7/Library/PNULib/sources/PNU_AND2.v">
      <FileInfo>
        <Attr Name="UsedInSynthesis" Val="1"/>
        <Attr Name="UsedInImplementation" Val="1"/>
        <Attr Name="UsedInSimulation" Val="1"/>
      </FileInfo>
    </File>
    <File Path="$PPRDIR/../../../Flowrian/Counter10.v">
      <FileInfo>
        <Attr Name="UsedInSynthesis" Val="1"/>
        <Attr Name="UsedInImplementation" Val="1"/>
        <Attr Name="UsedInSimulation" Val="1"/>
      </FileInfo>
    </File>
    <File Path="$PPRDIR/../../../../../../../Program Files/System Centroid/Flowrian R7/Library/PNULib/sources/PNU_NOR2.v">
      <FileInfo>
        <Attr Name="UsedInSynthesis" Val="1"/>
        <Attr Name="UsedInImplementation" Val="1"/>
        <Attr Name="UsedInSimulation" Val="1"/>
      </FileInfo>
    </File>
    <File Path="$PPRDIR/../../../Flowrian/eight_counter.v">
      <FileInfo>
        <Attr Name="UsedInSynthesis" Val="1"/>
        <Attr Name="UsedInImplementation" Val="1"/>
        <Attr Name="UsedInSimulation" Val="1"/>
      </FileInfo>
    </File>
    <File Path="$PPRDIR/../../../Flowrian/Decoder2bit.v">
      <FileInfo>
        <Attr Name="UsedInSynthesis" Val="1"/>
        <Attr Name="UsedInImplementation" Val="1"/>
        <Attr Name="UsedInSimulation" Val="1"/>
      </FileInfo>
    </File>
    <File Path="$PPRDIR/../../../Flowrian/Counter100.v">
      <FileInfo>
        <Attr Name="UsedInSynthesis" Val="1"/>
        <Attr Name="UsedInImplementation" Val="1"/>
        <Attr Name="UsedInSimulation" Val="1"/>
      </FileInfo>
    </File>
    <File Path="$PPRDIR/../../../../../../../Program Files/System Centroid/Flowrian R7/Library/PNULib/sources/PNU_ZERO.v">
      <FileInfo>
        <Attr Name="UsedInSynthesis" Val="1"/>
        <Attr Name="UsedInImplementation" Val="1"/>
        <Attr Name="UsedInSimulation" Val="1"/>
      </FileInfo>
    </File>
    <File Path="$PPRDIR/../../../../../../../Program Files/System Centroid/Flowrian R7/Library/PNULib/sources/PNU_MUX8.v">
      <FileInfo>
        <Attr Name="UsedInSynthesis" Val="1"/>
        <Attr Name="UsedInImplementation" Val="1"/>
        <Attr Name="UsedInSimulation" Val="1"/>
      </FileInfo>
    </File>
    <File Path="$PPRDIR/../../../../../../../Program Files/System Centroid/Flowrian R7/Library/PNULib/sources/PNU_MUX4.v">
      <FileInfo>
        <Attr Name="UsedInSynthesis" Val="1"/>
        <Attr Name="UsedInImplementation" Val="1"/>
        <Attr Name="UsedInSimulation" Val="1"/>
      </FileInfo>
    </File>
    <File Path="$PPRDIR/../../../../../../../Program Files/System Centroid/Flowrian R7/Library/PNULib/sources/PNU_MUX2.v">
      <FileInfo>
        <Attr Name="UsedInSynthesis" Val="1"/>
        <Attr Name="UsedInImplementation" Val="1"/>
        <Attr Name="UsedInSimulation" Val="1"/>
      </FileInfo>
    </File>
    <File Path="$PPRDIR/../../../Flowrian/PNU_CLK_DIV.v">
      <FileInfo>
        <Attr Name="UsedInSynthesis" Val="1"/>
        <Attr Name="UsedInImplementation" Val="1"/>
        <Attr Name="UsedInSimulation" Val="1"/>
      </FileInfo>
    </File>
    <File Path="$PPRDIR/../../../Flowrian/OR_7_7bits.v">
      <FileInfo>
        <Attr Name="UsedInSynthesis" Val="1"/>
        <Attr Name="UsedInImplementation" Val="1"/>
        <Attr Name="UsedInSimulation" Val="1"/>
      </FileInfo>
    </File>
    <File Path="$PPRDIR/../../../Flowrian/MUX4bit_4.v">
      <FileInfo>
        <Attr Name="UsedInSynthesis" Val="1"/>
        <Attr Name="UsedInImplementation" Val="1"/>
        <Attr Name="UsedInSimulation" Val="1"/>
      </FileInfo>
    </File>
    <File Path="$PPRDIR/../../../Flowrian/Mux12bit_4.v">
      <FileInfo>
        <Attr Name="UsedInSynthesis" Val="1"/>
        <Attr Name="UsedInImplementation" Val="1"/>
        <Attr Name="UsedInSimulation" Val="1"/>
      </FileInfo>
    </File>
    <File Path="$PPRDIR/../../../Flowrian/event_9.v">
      <FileInfo>
        <Attr Name="UsedInSynthesis" Val="1"/>
        <Attr Name="UsedInImplementation" Val="1"/>
        <Attr Name="UsedInSimulation" Val="1"/>
      </FileInfo>
    </File>
    <File Path="$PPRDIR/../../../Flowrian/event_8.v">
      <FileInfo>
        <Attr Name="UsedInSynthesis" Val="1"/>
        <Attr Name="UsedInImplementation" Val="1"/>
        <Attr Name="UsedInSimulation" Val="1"/>
      </FileInfo>
    </File>
    <File Path="$PPRDIR/../../../Flowrian/event_7.v">
      <FileInfo>
        <Attr Name="UsedInSynthesis" Val="1"/>
        <Attr Name="UsedInImplementation" Val="1"/>
        <Attr Name="UsedInSimulation" Val="1"/>
      </FileInfo>
    </File>
    <File Path="$PPRDIR/../../../Flowrian/event_5.v">
      <FileInfo>
        <Attr Name="UsedInSynthesis" Val="1"/>
        <Attr Name="UsedInImplementation" Val="1"/>
        <Attr Name="UsedInSimulation" Val="1"/>
      </FileInfo>
    </File>
    <File Path="$PPRDIR/../../../Flowrian/event_4.v">
      <FileInfo>
        <Attr Name="UsedInSynthesis" Val="1"/>
        <Attr Name="UsedInImplementation" Val="1"/>
        <Attr Name="UsedInSimulation" Val="1"/>
      </FileInfo>
    </File>
    <File Path="$PPRDIR/../../../Flowrian/event_3.v">
      <FileInfo>
        <Attr Name="UsedInSynthesis" Val="1"/>
        <Attr Name="UsedInImplementation" Val="1"/>
        <Attr Name="UsedInSimulation" Val="1"/>
      </FileInfo>
    </File>
    <File Path="$PPRDIR/../../../Flowrian/event_2.v">
      <FileInfo>
        <Attr Name="UsedInSynthesis" Val="1"/>
        <Attr Name="UsedInImplementation" Val="1"/>
        <Attr Name="UsedInSimulation" Val="1"/>
      </FileInfo>
    </File>
    <File Path="$PPRDIR/../../../Flowrian/event_12.v">
      <FileInfo>
        <Attr Name="UsedInSynthesis" Val="1"/>
        <Attr Name="UsedInImplementation" Val="1"/>
        <Attr Name="UsedInSimulation" Val="1"/>
      </FileInfo>
    </File>
    <File Path="$PPRDIR/../../../Flowrian/event_11.v">
      <FileInfo>
        <Attr Name="UsedInSynthesis" Val="1"/>
        <Attr Name="UsedInImplementation" Val="1"/>
        <Attr Name="UsedInSimulation" Val="1"/>
      </FileInfo>
    </File>
    <File Path="$PPRDIR/../../../Flowrian/event_10.v">
      <FileInfo>
        <Attr Name="UsedInSynthesis" Val="1"/>
        <Attr Name="UsedInImplementation" Val="1"/>
        <Attr Name="UsedInSimulation" Val="1"/>
      </FileInfo>
    </File>
    <File Path="$PPRDIR/../../../Flowrian/event_1.v">
      <FileInfo>
        <Attr Name="UsedInSynthesis" Val="1"/>
        <Attr Name="UsedInImplementation" Val="1"/>
        <Attr Name="UsedInSimulation" Val="1"/>
      </FileInfo>
    </File>
    <File Path="$PPRDIR/../../../Flowrian/Decoder3bit.v">
      <FileInfo>
        <Attr Name="UsedInSynthesis" Val="1"/>
        <Attr Name="UsedInImplementation" Val="1"/>
        <Attr Name="UsedInSimulation" Val="1"/>
      </FileInfo>
    </File>
    <File Path="$PPRDIR/../../../Flowrian/Counter10000.v">
      <FileInfo>
        <Attr Name="UsedInSynthesis" Val="1"/>
        <Attr Name="UsedInImplementation" Val="1"/>
        <Attr Name="UsedInSimulation" Val="1"/>
      </FileInfo>
    </File>
    <File Path="$PPRDIR/../../../Flowrian/AND_7bit.v">
      <FileInfo>
        <Attr Name="UsedInSynthesis" Val="1"/>
        <Attr Name="UsedInImplementation" Val="1"/>
        <Attr Name="UsedInSimulation" Val="1"/>
      </FileInfo>
    </File>
    <File Path="$PPRDIR/../../../../../../../Program Files/System Centroid/Flowrian R7/Library/PNULib/sources/PNU_OR4.v">
      <FileInfo>
        <Attr Name="UsedInSynthesis" Val="1"/>
        <Attr Name="UsedInImplementation" Val="1"/>
        <Attr Name="UsedInSimulation" Val="1"/>
      </FileInfo>
    </File>
    <File Path="$PPRDIR/../../../../../../../Program Files/System Centroid/Flowrian R7/Library/PNULib/sources/PNU_DFF_Ce.v">
      <FileInfo>
        <Attr Name="UsedInSynthesis" Val="1"/>
        <Attr Name="UsedInImplementation" Val="1"/>
        <Attr Name="UsedInSimulation" Val="1"/>
      </FileInfo>
    </File>
    <File Path="$PPRDIR/../../../../../../../Program Files/System Centroid/Flowrian R7/Library/PNULib/sources/PNU_AND4.v">
      <FileInfo>
        <Attr Name="UsedInSynthesis" Val="1"/>
        <Attr Name="UsedInImplementation" Val="1"/>
        <Attr Name="UsedInSimulation" Val="1"/>
      </FileInfo>
    </File>
    <File Path="$PPRDIR/../../../Flowrian/ToneConverter.v">
      <FileInfo>
        <Attr Name="UsedInSynthesis" Val="1"/>
        <Attr Name="UsedInImplementation" Val="1"/>
        <Attr Name="UsedInSimulation" Val="1"/>
      </FileInfo>
    </File>
    <File Path="$PPRDIR/../../../Flowrian/Segments8_Handler.v">
      <FileInfo>
        <Attr Name="UsedInSynthesis" Val="1"/>
        <Attr Name="UsedInImplementation" Val="1"/>
        <Attr Name="UsedInSimulation" Val="1"/>
      </FileInfo>
    </File>
    <File Path="$PPRDIR/../../../Flowrian/RGB_Handler.v">
      <FileInfo>
        <Attr Name="UsedInSynthesis" Val="1"/>
        <Attr Name="UsedInImplementation" Val="1"/>
        <Attr Name="UsedInSimulation" Val="1"/>
      </FileInfo>
    </File>
    <File Path="$PPRDIR/../../../Flowrian/register.v">
      <FileInfo>
        <Attr Name="UsedInSynthesis" Val="1"/>
        <Attr Name="UsedInImplementation" Val="1"/>
        <Attr Name="UsedInSimulation" Val="1"/>
      </FileInfo>
    </File>
    <File Path="$PPRDIR/../../../Flowrian/MUX4bit_16.v">
      <FileInfo>
        <Attr Name="UsedInSynthesis" Val="1"/>
        <Attr Name="UsedInImplementation" Val="1"/>
        <Attr Name="UsedInSimulation" Val="1"/>
      </FileInfo>
    </File>
    <File Path="$PPRDIR/../../../Flowrian/LED_Handler.v">
      <FileInfo>
        <Attr Name="UsedInSynthesis" Val="1"/>
        <Attr Name="UsedInImplementation" Val="1"/>
        <Attr Name="UsedInSimulation" Val="1"/>
      </FileInfo>
    </File>
    <File Path="$PPRDIR/../../../Flowrian/event_6.v">
      <FileInfo>
        <Attr Name="UsedInSynthesis" Val="1"/>
        <Attr Name="UsedInImplementation" Val="1"/>
        <Attr Name="UsedInSimulation" Val="1"/>
      </FileInfo>
    </File>
    <File Path="$PPRDIR/../../../Flowrian/Decoder4bits.v">
      <FileInfo>
        <Attr Name="UsedInSynthesis" Val="1"/>
        <Attr Name="UsedInImplementation" Val="1"/>
        <Attr Name="UsedInSimulation" Val="1"/>
      </FileInfo>
    </File>
    <File Path="$PPRDIR/../../../Flowrian/Counter20000.v">
      <FileInfo>
        <Attr Name="UsedInSynthesis" Val="1"/>
        <Attr Name="UsedInImplementation" Val="1"/>
        <Attr Name="UsedInSimulation" Val="1"/>
      </FileInfo>
    </File>
    <File Path="$PPRDIR/../../../../../../../Program Files/System Centroid/Flowrian R7/Library/PNULib/sources/PNU_OR8.v">
      <FileInfo>
        <Attr Name="UsedInSynthesis" Val="1"/>
        <Attr Name="UsedInImplementation" Val="1"/>
        <Attr Name="UsedInSimulation" Val="1"/>
      </FileInfo>
    </File>
    <File Path="$PPRDIR/../../../Flowrian/SRAM12bits.v">
      <FileInfo>
        <Attr Name="UsedInSynthesis" Val="1"/>
        <Attr Name="UsedInImplementation" Val="1"/>
        <Attr Name="UsedInSimulation" Val="1"/>
      </FileInfo>
    </File>
    <File Path="$PPRDIR/../../../Flowrian/PriorityEncoder3.v">
      <FileInfo>
        <Attr Name="UsedInSynthesis" Val="1"/>
        <Attr Name="UsedInImplementation" Val="1"/>
        <Attr Name="UsedInSimulation" Val="1"/>
      </FileInfo>
    </File>
    <File Path="$PPRDIR/../../../Flowrian/PianoPlay.v">
      <FileInfo>
        <Attr Name="UsedInSynthesis" Val="1"/>
        <Attr Name="UsedInImplementation" Val="1"/>
        <Attr Name="UsedInSimulation" Val="1"/>
      </FileInfo>
    </File>
    <File Path="$PPRDIR/../../../Flowrian/mod_converter.v">
      <FileInfo>
        <Attr Name="UsedInSynthesis" Val="1"/>
        <Attr Name="UsedInImplementation" Val="1"/>
        <Attr Name="UsedInSimulation" Val="1"/>
      </FileInfo>
    </File>
    <File Path="$PPRDIR/../../../Flowrian/EventHandler.v">
      <FileInfo>
        <Attr Name="UsedInSynthesis" Val="1"/>
        <Attr Name="UsedInImplementation" Val="1"/>
        <Attr Name="UsedInSimulation" Val="1"/>
      </FileInfo>
    </File>
    <File Path="$PPRDIR/../../../Flowrian/encoder_12_to_4.v">
      <FileInfo>
        <Attr Name="UsedInSynthesis" Val="1"/>
        <Attr Name="UsedInImplementation" Val="1"/>
        <Attr Name="UsedInSimulation" Val="1"/>
      </FileInfo>
    </File>
    <File Path="$PPRDIR/../../../Flowrian/Accumulator.v">
      <FileInfo>
        <Attr Name="UsedInSynthesis" Val="1"/>
        <Attr Name="UsedInImplementation" Val="1"/>
        <Attr Name="UsedInSimulation" Val="1"/>
      </FileInfo>
    </File>
    <File Path="$PPRDIR/../../../Flowrian/LaunchPad.v">
      <FileInfo>
        <Attr Name="UsedInSynthesis" Val="1"/>
        <Attr Name="UsedInImplementation" Val="1"/>
        <Attr Name="UsedInSimulation" Val="1"/>
      </FileInfo>
    </File>
    <Config>
      <Option Name="DesignMode" Val="RTL"/>
      <Option Name="TopModule" Val="LaunchPad"/>
    </Config>
  </FileSet>
</DARoots>
